llm_tool-1.0.7.dist-info/METADATA
llm_tool-1.0.7.dist-info/WHEEL
llm_tool-1.0.7.dist-info/licenses/LICENSE
llm_tool.libs/libgcc_s-5b5488a6.so.1
llm_tool/__init__.py
llm_tool/tool.py
llm_tool/llm_tool.pypy310-pp73-arm-linux-gnu.so
llm_tool-1.0.7.dist-info/RECORD
